{
  "week": "2026-W24",
  "start_date": "2026-06-08",
  "end_date": "2026-06-14",
  "label": "Semana 24 · 2026",
  "date_range": "8 — 14 Jun 2026",
  "playlist_url": "https://open.spotify.com/playlist/3iHETIGrWBdoY3a8jNrMox",
  "tracks": [
    {
      "rank": 1,
      "artist": "Paycheque",
      "title": "Heatwave",
      "source": "Gorilla vs Bear",
      "source_count": 1,
      "spotify_url": "https://open.spotify.com/track/3l8uXR5okOwmQxAfO3xiAZ"
    },
    {
      "rank": 2,
      "artist": "Marci",
      "title": "Butterfly Sticker",
      "source": "Gorilla vs Bear",
      "source_count": 1,
      "spotify_url": "https://open.spotify.com/track/3tCJl3lsma79PYa4Wwblss"
    },
    {
      "rank": 3,
      "artist": "Snag",
      "title": "Unarrest Me",
      "source": "Stereogum",
      "source_count": 1,
      "spotify_url": "https://open.spotify.com/track/2umtuon9L2esTDr3mrAWKh"
    },
    {
      "rank": 4,
      "artist": "Hank Heaven",
      "title": "Thread",
      "source": "Stereogum",
      "source_count": 1,
      "spotify_url": "https://open.spotify.com/track/2NMLvHZYJSLxgohwDt3oXx"
    },
    {
      "rank": 5,
      "artist": "Hovvdy",
      "title": "Blast",
      "source": "Stereogum",
      "source_count": 1,
      "spotify_url": "https://open.spotify.com/track/6iDEHohlNFZ6iMN4pqmFq0"
    },
    {
      "rank": 6,
      "artist": "Gloorp",
      "title": "Ice Bath",
      "source": "Stereogum",
      "source_count": 1,
      "spotify_url": "https://open.spotify.com/track/4Elamq934Wl1jtThq5bAkO"
    },
    {
      "rank": 7,
      "artist": "Six Sex",
      "title": "ULTRA",
      "source": "NPR",
      "source_count": 1,
      "spotify_url": "https://open.spotify.com/track/4OYdQQQQ26Zg1PJS4oXyIf"
    }
  ],
  "albums": [
    {
      "rank": 1,
      "artist": "Zoh Amba",
      "title": "Eyes Full",
      "source": "The Guardian",
      "source_count": 1,
      "link": "https://www.theguardian.com/music/2026/jun/05/zoh-amba-eyes-full-review-country-rock-matador",
      "spotify_url": null
    },
    {
      "rank": 2,
      "artist": "Gintė Preisaitė",
      "title": "Instruments of Forgetting and the Singing Bone",
      "source": "The Guardian",
      "source_count": 1,
      "link": "https://www.theguardian.com/music/2026/jun/05/ginte-preisaite-instruments-of-forgetting-and-the-singing-bone-review",
      "spotify_url": null
    },
    {
      "rank": 3,
      "artist": "Olivia Rodrigo",
      "title": "You Seem Pretty Sad for a Girl So in Love",
      "source": "The Guardian",
      "source_count": 1,
      "link": "https://www.theguardian.com/music/2026/jun/12/olivia-rodrigo-you-seem-pretty-sad-for-a-girl-so-in-love-album-review",
      "spotify_url": null
    },
    {
      "rank": 4,
      "artist": "Káryyn",
      "title": "Physics Universal Love Language (PULL)",
      "source": "The Quietus",
      "source_count": 1,
      "link": "https://thequietus.com/quietus-reviews/karyyn-physics-universal-love-language-pull-review/?utm_source=rss&utm_medium=rss&utm_campaign=karyyn-physics-universal-love-language-pull-review",
      "spotify_url": null
    },
    {
      "rank": 5,
      "artist": "Vince Staples",
      "title": "Cry Baby",
      "source": "The Quietus",
      "source_count": 1,
      "link": "https://thequietus.com/quietus-reviews/vince-staples-cry-baby-review/?utm_source=rss&utm_medium=rss&utm_campaign=vince-staples-cry-baby-review",
      "spotify_url": null
    },
    {
      "rank": 6,
      "artist": "Bill Orcutt & Mabe Fratti",
      "title": "Almost Waking",
      "source": "The Quietus",
      "source_count": 1,
      "link": "https://thequietus.com/quietus-reviews/bill-orcutt-mabe-fratti-almost-waking-review/?utm_source=rss&utm_medium=rss&utm_campaign=bill-orcutt-mabe-fratti-almost-waking-review",
      "spotify_url": null
    },
    {
      "rank": 7,
      "artist": "YHWH Nailgun",
      "title": "Magazine",
      "source": "The Quietus",
      "source_count": 1,
      "link": "https://thequietus.com/quietus-reviews/yhwh-nailgun-magazine-review/?utm_source=rss&utm_medium=rss&utm_campaign=yhwh-nailgun-magazine-review",
      "spotify_url": null
    }
  ],
  "sources": [
    "Gorilla vs Bear",
    "Stereogum",
    "NPR",
    "The Guardian",
    "The Quietus"
  ]
}
